aiorp/__init__.py
aiorp/base_handler.py
aiorp/context.py
aiorp/http_handler.py
aiorp/request.py
aiorp/response.py
aiorp/rewrite.py
aiorp/ws_handler.py
aiorp-0.1.2.dist-info/METADATA
aiorp-0.1.2.dist-info/WHEEL
aiorp-0.1.2.dist-info/licenses/LICENSE
aiorp-0.1.2.dist-info/RECORD
