Metadata-Version: 2.4
Name: aiorp
Version: 0.1.2
Summary: A simple reverse proxy library based on aiohttp.
License-File: LICENSE
Requires-Python: >=3.10
Requires-Dist: aiohttp>=3.11.12
